{
  "metadata": {
    "source_book": "STANDARDS BOOK II vol. I_REV0",
    "source_page": 3,
    "extractor": "DesignRuleExtractor",
    "extraction_type": "design_rule"
  },
  "title": "(Standard Design Manual) - Downloaded By: David Cornealius, At: 2025-12-25 14:53",
  "rules": [
    {
      "step_number": 5938,
      "description": "Distribution:",
      "type": "procedure_step"
    },
    {
      "step_number": 1,
      "description": "Castillo 122-HPM, Ramos 138-J. Trevathan",
      "type": "procedure_step"
    },
    {
      "step_number": 1,
      "description": "Lohman 110-HPM, Ramos 124-R. Waclawski 141-M. LeBlanc",
      "type": "procedure_step"
    }
  ],
  "rule_type": "procedure"
}